muslib-0.1.1.dist-info/METADATA
muslib-0.1.1.dist-info/WHEEL
muslib/__init__.py
muslib/muslib.abi3.so
muslib-0.1.1.dist-info/RECORD
