Metadata-Version: 2.1
Name: muslib
Version: 0.1.1
Summary: Rust library for music synthesis and processing, inspired by Essentia.
Keywords: music
Author: Wiktor W. <wykwit@disroot.org>
Author-email: Wiktor W. <wykwit@disroot.org>
License: AGPL-3.0-or-later
Project-URL: Source Code, https://gitlab.com/wykwit/muslib/
